featureflagshq/__init__.py
featureflagshq/sdk.py
featureflagshq-1.0.1.dist-info/licenses/LICENSE
featureflagshq-1.0.1.dist-info/METADATA
featureflagshq-1.0.1.dist-info/WHEEL
featureflagshq-1.0.1.dist-info/top_level.txt
featureflagshq-1.0.1.dist-info/RECORD
