Metadata-Version: 2.4
Name: featureflagshq
Version: 1.0.1
Summary: A secure, high-performance Python SDK for FeatureFlagsHQ feature flag management
Home-page: https://github.com/featureflagshq/python-sdk
Author: FeatureFlagsHQ
Author-email: FeatureFlagsHQ <hello@featureflagshq.com>
License: MIT
Project-URL: Homepage, https://featureflagshq.com
Project-URL: Documentation, https://featureflagshq.com/documentation/
Project-URL: Repository, https://github.com/featureflagshq/python-sdk
Project-URL: Bug Tracker, https://github.com/featureflagshq/python-sdk/issues
Keywords: feature flags,feature toggles,experimentation,a/b testing
Classifier: Development Status :: 5 - Production/Stable
Classifier: Intended Audience :: Developers
Classifier: License :: OSI Approved :: MIT License
Classifier: Operating System :: OS Independent
Classifier: Programming Language :: Python :: 3
Classifier: Programming Language :: Python :: 3.7
Classifier: Programming Language :: Python :: 3.8
Classifier: Programming Language :: Python :: 3.9
Classifier: Programming Language :: Python :: 3.10
Classifier: Programming Language :: Python :: 3.11
Classifier: Programming Language :: Python :: 3.12
Requires-Python: >=3.7
License-File: LICENSE
Requires-Dist: requests>=2.25.0
Provides-Extra: dev
Requires-Dist: pytest>=6.0; extra == "dev"
Requires-Dist: pytest-cov>=2.0; extra == "dev"
Requires-Dist: black>=21.0; extra == "dev"
Requires-Dist: flake8>=3.8; extra == "dev"
Requires-Dist: mypy>=0.812; extra == "dev"
Requires-Dist: responses>=0.18.0; extra == "dev"
Requires-Dist: twine>=3.0; extra == "dev"
Requires-Dist: build>=0.7.0; extra == "dev"
Dynamic: author
Dynamic: home-page
Dynamic: license-file
Dynamic: requires-python
